{"npi":"1023382033","totalPaid":23986265.75,"totalClaims":25397,"totalBeneficiaries":21570,"uniqueCodes":4,"activeMonths":83,"procedures":[{"code":"H0039","totalPaid":23953827.65,"totalClaims":24355,"uniqueBeneficiaries":20841},{"code":"90791","totalPaid":30638.1,"totalClaims":733,"uniqueBeneficiaries":557},{"code":"H0031","totalPaid":1800.0,"totalClaims":13,"uniqueBeneficiaries":12},{"code":"98960","totalPaid":0.0,"totalClaims":296,"uniqueBeneficiaries":160}],"monthlyTrend":[{"month":"2018-01","totalPaid":187030.39,"totalClaims":196},{"month":"2018-02","totalPaid":181968.85,"totalClaims":196},{"month":"2018-03","totalPaid":187464.97,"totalClaims":209},{"month":"2018-04","totalPaid":181808.18,"totalClaims":226},{"month":"2018-05","totalPaid":195035.63,"totalClaims":232},{"month":"2018-06","totalPaid":194352.26,"totalClaims":251},{"month":"2018-07","totalPaid":141145.77,"totalClaims":491},{"month":"2018-08","totalPaid":183210.17,"totalClaims":310},{"month":"2018-09","totalPaid":182380.9,"totalClaims":324},{"month":"2018-10","totalPaid":199769.09,"totalClaims":334},{"month":"2018-11","totalPaid":198280.2,"totalClaims":304},{"month":"2018-12","totalPaid":210409.61,"totalClaims":381},{"month":"2019-01","totalPaid":215100.25,"totalClaims":278},{"month":"2019-02","totalPaid":225265.24,"totalClaims":397},{"month":"2019-03","totalPaid":232974.4,"totalClaims":278},{"month":"2019-04","totalPaid":247718.18,"totalClaims":292},{"month":"2019-05","totalPaid":271297.39,"totalClaims":295},{"month":"2019-06","totalPaid":256506.86,"totalClaims":298},{"month":"2019-07","totalPaid":242638.24,"totalClaims":269},{"month":"2019-08","totalPaid":247179.56,"totalClaims":304},{"month":"2019-09","totalPaid":262956.45,"totalClaims":320},{"month":"2019-10","totalPaid":263624.73,"totalClaims":278},{"month":"2019-11","totalPaid":260895.78,"totalClaims":260},{"month":"2019-12","totalPaid":267801.21,"totalClaims":273},{"month":"2020-01","totalPaid":262885.03,"totalClaims":271},{"month":"2020-02","totalPaid":264794.7,"totalClaims":264},{"month":"2020-03","totalPaid":273294.49,"totalClaims":289},{"month":"2020-04","totalPaid":281729.13,"totalClaims":323},{"month":"2020-05","totalPaid":286683.44,"totalClaims":288},{"month":"2020-06","totalPaid":296269.86,"totalClaims":301},{"month":"2020-07","totalPaid":291498.48,"totalClaims":336},{"month":"2020-08","totalPaid":307985.48,"totalClaims":340},{"month":"2020-09","totalPaid":309755.64,"totalClaims":337},{"month":"2020-10","totalPaid":321955.14,"totalClaims":375},{"month":"2020-11","totalPaid":315362.42,"totalClaims":330},{"month":"2020-12","totalPaid":314740.51,"totalClaims":317},{"month":"2021-01","totalPaid":313550.73,"totalClaims":327},{"month":"2021-02","totalPaid":306685.56,"totalClaims":321},{"month":"2021-03","totalPaid":315142.64,"totalClaims":344},{"month":"2021-04","totalPaid":305631.79,"totalClaims":326},{"month":"2021-05","totalPaid":305699.16,"totalClaims":350},{"month":"2021-06","totalPaid":303006.49,"totalClaims":361},{"month":"2021-07","totalPaid":299480.51,"totalClaims":342},{"month":"2021-08","totalPaid":296875.03,"totalClaims":357},{"month":"2021-09","totalPaid":303394.91,"totalClaims":349},{"month":"2021-10","totalPaid":292235.64,"totalClaims":308},{"month":"2021-11","totalPaid":283919.68,"totalClaims":310},{"month":"2021-12","totalPaid":280124.31,"totalClaims":306},{"month":"2022-01","totalPaid":258987.04,"totalClaims":267},{"month":"2022-02","totalPaid":267262.99,"totalClaims":272},{"month":"2022-03","totalPaid":260072.87,"totalClaims":269},{"month":"2022-04","totalPaid":278413.1,"totalClaims":281},{"month":"2022-05","totalPaid":283821.91,"totalClaims":339},{"month":"2022-06","totalPaid":286058.27,"totalClaims":289},{"month":"2022-07","totalPaid":271293.17,"totalClaims":261},{"month":"2022-08","totalPaid":260641.69,"totalClaims":326},{"month":"2022-09","totalPaid":267104.48,"totalClaims":318},{"month":"2022-10","totalPaid":252056.53,"totalClaims":258},{"month":"2022-11","totalPaid":245640.87,"totalClaims":311},{"month":"2022-12","totalPaid":230766.44,"totalClaims":274},{"month":"2023-01","totalPaid":245425.05,"totalClaims":263},{"month":"2023-02","totalPaid":251324.4,"totalClaims":333},{"month":"2023-03","totalPaid":268276.47,"totalClaims":300},{"month":"2023-04","totalPaid":277573.07,"totalClaims":302},{"month":"2023-05","totalPaid":292720.62,"totalClaims":344},{"month":"2023-06","totalPaid":294771.75,"totalClaims":334},{"month":"2023-07","totalPaid":287793.16,"totalClaims":308},{"month":"2023-08","totalPaid":294646.8,"totalClaims":386},{"month":"2023-09","totalPaid":295918.98,"totalClaims":340},{"month":"2023-10","totalPaid":436786.68,"totalClaims":297},{"month":"2023-11","totalPaid":425540.23,"totalClaims":318},{"month":"2023-12","totalPaid":426927.07,"totalClaims":312},{"month":"2024-01","totalPaid":428374.05,"totalClaims":354},{"month":"2024-02","totalPaid":433506.13,"totalClaims":316},{"month":"2024-03","totalPaid":424262.16,"totalClaims":288},{"month":"2024-04","totalPaid":409348.94,"totalClaims":354},{"month":"2024-05","totalPaid":412544.22,"totalClaims":290},{"month":"2024-06","totalPaid":435012.35,"totalClaims":300},{"month":"2024-07","totalPaid":431140.0,"totalClaims":299},{"month":"2024-08","totalPaid":427531.18,"totalClaims":305},{"month":"2024-09","totalPaid":419199.0,"totalClaims":276},{"month":"2024-10","totalPaid":404654.0,"totalClaims":266},{"month":"2024-11","totalPaid":431355.0,"totalClaims":279}]}