{
  "npi": "1053453951",
  "totalPaid": 39982519.32,
  "totalClaims": 411942,
  "totalBeneficiaries": 355748,
  "uniqueCodes": 11,
  "activeMonths": 84,
  "procedures": [
    {
      "code": "A0427",
      "totalPaid": 24649410.06,
      "totalClaims": 112208,
      "uniqueBeneficiaries": 98490
    },
    {
      "code": "A0429",
      "totalPaid": 13255113.38,
      "totalClaims": 62291,
      "uniqueBeneficiaries": 54198
    },
    {
      "code": "A0425",
      "totalPaid": 1659259.37,
      "totalClaims": 171821,
      "uniqueBeneficiaries": 147527
    },
    {
      "code": "A0424",
      "totalPaid": 290102.48,
      "totalClaims": 24489,
      "uniqueBeneficiaries": 22274
    },
    {
      "code": "93005",
      "totalPaid": 51077.6,
      "totalClaims": 8113,
      "uniqueBeneficiaries": 7745
    },
    {
      "code": "A0422",
      "totalPaid": 46813.9,
      "totalClaims": 6393,
      "uniqueBeneficiaries": 5978
    },
    {
      "code": "A0433",
      "totalPaid": 14794.57,
      "totalClaims": 74,
      "uniqueBeneficiaries": 73
    },
    {
      "code": "A0999",
      "totalPaid": 11163.49,
      "totalClaims": 21704,
      "uniqueBeneficiaries": 15120
    },
    {
      "code": "A0398",
      "totalPaid": 3739.21,
      "totalClaims": 3407,
      "uniqueBeneficiaries": 3047
    },
    {
      "code": "A0382",
      "totalPaid": 829.61,
      "totalClaims": 1424,
      "uniqueBeneficiaries": 1278
    },
    {
      "code": "93041",
      "totalPaid": 215.65,
      "totalClaims": 18,
      "uniqueBeneficiaries": 18
    }
  ],
  "monthlyTrend": [
    {
      "month": "2018-01",
      "totalPaid": 232671.6,
      "totalClaims": 6368
    },
    {
      "month": "2018-02",
      "totalPaid": 215591.92,
      "totalClaims": 5572
    },
    {
      "month": "2018-03",
      "totalPaid": 243265.47,
      "totalClaims": 6020
    },
    {
      "month": "2018-04",
      "totalPaid": 227402.32,
      "totalClaims": 5621
    },
    {
      "month": "2018-05",
      "totalPaid": 199971.63,
      "totalClaims": 5094
    },
    {
      "month": "2018-06",
      "totalPaid": 146115.39,
      "totalClaims": 4168
    },
    {
      "month": "2018-07",
      "totalPaid": 485478.8,
      "totalClaims": 5950
    },
    {
      "month": "2018-08",
      "totalPaid": 514767.34,
      "totalClaims": 6833
    },
    {
      "month": "2018-09",
      "totalPaid": 488446.3,
      "totalClaims": 6748
    },
    {
      "month": "2018-10",
      "totalPaid": 506209.83,
      "totalClaims": 6752
    },
    {
      "month": "2018-11",
      "totalPaid": 485948.22,
      "totalClaims": 6338
    },
    {
      "month": "2018-12",
      "totalPaid": 487432.84,
      "totalClaims": 6274
    },
    {
      "month": "2019-01",
      "totalPaid": 509712.65,
      "totalClaims": 6196
    },
    {
      "month": "2019-02",
      "totalPaid": 604582.64,
      "totalClaims": 6087
    },
    {
      "month": "2019-03",
      "totalPaid": 702107.39,
      "totalClaims": 6919
    },
    {
      "month": "2019-04",
      "totalPaid": 662028.33,
      "totalClaims": 6366
    },
    {
      "month": "2019-05",
      "totalPaid": 715682.59,
      "totalClaims": 6467
    },
    {
      "month": "2019-06",
      "totalPaid": 677863.33,
      "totalClaims": 6218
    },
    {
      "month": "2019-07",
      "totalPaid": 598872.58,
      "totalClaims": 5767
    },
    {
      "month": "2019-08",
      "totalPaid": 591927.25,
      "totalClaims": 5718
    },
    {
      "month": "2019-09",
      "totalPaid": 605998.72,
      "totalClaims": 5760
    },
    {
      "month": "2019-10",
      "totalPaid": 615991.91,
      "totalClaims": 5929
    },
    {
      "month": "2019-11",
      "totalPaid": 630708.51,
      "totalClaims": 5557
    },
    {
      "month": "2019-12",
      "totalPaid": 701571.44,
      "totalClaims": 6077
    },
    {
      "month": "2020-01",
      "totalPaid": 643193.22,
      "totalClaims": 5385
    },
    {
      "month": "2020-02",
      "totalPaid": 602509.06,
      "totalClaims": 5213
    },
    {
      "month": "2020-03",
      "totalPaid": 567121.71,
      "totalClaims": 4735
    },
    {
      "month": "2020-04",
      "totalPaid": 375992.52,
      "totalClaims": 3196
    },
    {
      "month": "2020-05",
      "totalPaid": 488652.05,
      "totalClaims": 4000
    },
    {
      "month": "2020-06",
      "totalPaid": 603158.9,
      "totalClaims": 4929
    },
    {
      "month": "2020-07",
      "totalPaid": 702407.5,
      "totalClaims": 5518
    },
    {
      "month": "2020-08",
      "totalPaid": 722726.31,
      "totalClaims": 5711
    },
    {
      "month": "2020-09",
      "totalPaid": 729718.42,
      "totalClaims": 5802
    },
    {
      "month": "2020-10",
      "totalPaid": 712195.5,
      "totalClaims": 5778
    },
    {
      "month": "2020-11",
      "totalPaid": 652237.5,
      "totalClaims": 5220
    },
    {
      "month": "2020-12",
      "totalPaid": 714608.07,
      "totalClaims": 5741
    },
    {
      "month": "2021-01",
      "totalPaid": 596266.47,
      "totalClaims": 4916
    },
    {
      "month": "2021-02",
      "totalPaid": 549420.95,
      "totalClaims": 4579
    },
    {
      "month": "2021-03",
      "totalPaid": 669189.45,
      "totalClaims": 5551
    },
    {
      "month": "2021-04",
      "totalPaid": 620650.4,
      "totalClaims": 5174
    },
    {
      "month": "2021-05",
      "totalPaid": 614841.67,
      "totalClaims": 5150
    },
    {
      "month": "2021-06",
      "totalPaid": 662226.59,
      "totalClaims": 5639
    },
    {
      "month": "2021-07",
      "totalPaid": 640658.41,
      "totalClaims": 5382
    },
    {
      "month": "2021-08",
      "totalPaid": 614533.35,
      "totalClaims": 5154
    },
    {
      "month": "2021-09",
      "totalPaid": 613728.47,
      "totalClaims": 5142
    },
    {
      "month": "2021-10",
      "totalPaid": 584026.68,
      "totalClaims": 4780
    },
    {
      "month": "2021-11",
      "totalPaid": 527153.9,
      "totalClaims": 4423
    },
    {
      "month": "2021-12",
      "totalPaid": 488823.19,
      "totalClaims": 4079
    },
    {
      "month": "2022-01",
      "totalPaid": 402199.07,
      "totalClaims": 3717
    },
    {
      "month": "2022-02",
      "totalPaid": 393710.58,
      "totalClaims": 3629
    },
    {
      "month": "2022-03",
      "totalPaid": 462487.37,
      "totalClaims": 4338
    },
    {
      "month": "2022-04",
      "totalPaid": 481899.18,
      "totalClaims": 4507
    },
    {
      "month": "2022-05",
      "totalPaid": 495128.16,
      "totalClaims": 4553
    },
    {
      "month": "2022-06",
      "totalPaid": 502287.57,
      "totalClaims": 4639
    },
    {
      "month": "2022-07",
      "totalPaid": 491175.26,
      "totalClaims": 4575
    },
    {
      "month": "2022-08",
      "totalPaid": 471240.87,
      "totalClaims": 4542
    },
    {
      "month": "2022-09",
      "totalPaid": 495524.15,
      "totalClaims": 4591
    },
    {
      "month": "2022-10",
      "totalPaid": 441490.66,
      "totalClaims": 4059
    },
    {
      "month": "2022-11",
      "totalPaid": 411579.48,
      "totalClaims": 3992
    },
    {
      "month": "2022-12",
      "totalPaid": 424099.21,
      "totalClaims": 4199
    },
    {
      "month": "2023-01",
      "totalPaid": 429549.76,
      "totalClaims": 4121
    },
    {
      "month": "2023-02",
      "totalPaid": 362946.01,
      "totalClaims": 3801
    },
    {
      "month": "2023-03",
      "totalPaid": 411932.74,
      "totalClaims": 4265
    },
    {
      "month": "2023-04",
      "totalPaid": 393060.5,
      "totalClaims": 4427
    },
    {
      "month": "2023-05",
      "totalPaid": 390930.37,
      "totalClaims": 4116
    },
    {
      "month": "2023-06",
      "totalPaid": 386128.47,
      "totalClaims": 3990
    },
    {
      "month": "2023-07",
      "totalPaid": 421067.31,
      "totalClaims": 4501
    },
    {
      "month": "2023-08",
      "totalPaid": 431645.48,
      "totalClaims": 5148
    },
    {
      "month": "2023-09",
      "totalPaid": 408058.23,
      "totalClaims": 5072
    },
    {
      "month": "2023-10",
      "totalPaid": 407394,
      "totalClaims": 5046
    },
    {
      "month": "2023-11",
      "totalPaid": 396030.32,
      "totalClaims": 4630
    },
    {
      "month": "2023-12",
      "totalPaid": 329751.7,
      "totalClaims": 4927
    },
    {
      "month": "2024-01",
      "totalPaid": 298189.09,
      "totalClaims": 4294
    },
    {
      "month": "2024-02",
      "totalPaid": 288941.27,
      "totalClaims": 4294
    },
    {
      "month": "2024-03",
      "totalPaid": 330598.74,
      "totalClaims": 3891
    },
    {
      "month": "2024-04",
      "totalPaid": 346211.12,
      "totalClaims": 3895
    },
    {
      "month": "2024-05",
      "totalPaid": 364271.37,
      "totalClaims": 4324
    },
    {
      "month": "2024-06",
      "totalPaid": 369125.07,
      "totalClaims": 4069
    },
    {
      "month": "2024-07",
      "totalPaid": 332583.24,
      "totalClaims": 4261
    },
    {
      "month": "2024-08",
      "totalPaid": 271916.85,
      "totalClaims": 3661
    },
    {
      "month": "2024-09",
      "totalPaid": 279003.53,
      "totalClaims": 3406
    },
    {
      "month": "2024-10",
      "totalPaid": 199037.95,
      "totalClaims": 2911
    },
    {
      "month": "2024-11",
      "totalPaid": 104153.83,
      "totalClaims": 1489
    },
    {
      "month": "2024-12",
      "totalPaid": 10781.52,
      "totalClaims": 66
    }
  ],
  "name": "WESTMED AMBULANCE INC",
  "city": "COMPTON",
  "state": "CA",
  "specialty": "Ambulance"
}