{"npi":"1215048913","totalPaid":11519064.24,"totalClaims":802199,"totalBeneficiaries":765485,"uniqueCodes":169,"activeMonths":84,"procedures":[{"code":"U0003","totalPaid":2307140.48,"totalClaims":33644,"uniqueBeneficiaries":31566},{"code":"87491","totalPaid":741822.27,"totalClaims":24306,"uniqueBeneficiaries":23349},{"code":"87591","totalPaid":736389.67,"totalClaims":24073,"uniqueBeneficiaries":23118},{"code":"U0005","totalPaid":533110.8,"totalClaims":24972,"uniqueBeneficiaries":23384},{"code":"86481","totalPaid":467388.57,"totalClaims":4998,"uniqueBeneficiaries":4874},{"code":"87389","totalPaid":462804.64,"totalClaims":21221,"uniqueBeneficiaries":20829},{"code":"84443","totalPaid":407838.12,"totalClaims":35909,"uniqueBeneficiaries":35105},{"code":"80307","totalPaid":387516.07,"totalClaims":7343,"uniqueBeneficiaries":7007},{"code":"83036","totalPaid":343889.89,"totalClaims":53696,"uniqueBeneficiaries":52761},{"code":"82306","totalPaid":318339.02,"totalClaims":14935,"uniqueBeneficiaries":14658},{"code":"80061","totalPaid":271990.28,"totalClaims":33082,"uniqueBeneficiaries":32460},{"code":"80048","totalPaid":219544.22,"totalClaims":44032,"uniqueBeneficiaries":41647},{"code":"86780","totalPaid":209179.08,"totalClaims":17498,"uniqueBeneficiaries":17216},{"code":"87624","totalPaid":208676.4,"totalClaims":6890,"uniqueBeneficiaries":6781},{"code":"86803","totalPaid":169009.17,"totalClaims":12477,"uniqueBeneficiaries":12236},{"code":"80053","totalPaid":145496.5,"totalClaims":20064,"uniqueBeneficiaries":19417},{"code":"82728","totalPaid":142718.79,"totalClaims":13855,"uniqueBeneficiaries":13537},{"code":"87340","totalPaid":112380.77,"totalClaims":11800,"uniqueBeneficiaries":11554},{"code":"82607","totalPaid":108287.61,"totalClaims":10083,"uniqueBeneficiaries":9929},{"code":"87086","totalPaid":107886.15,"totalClaims":18253,"uniqueBeneficiaries":17310},{"code":"G0480","totalPaid":105383.98,"totalClaims":1701,"uniqueBeneficiaries":1555},{"code":"G0123","totalPaid":97236.19,"totalClaims":5448,"uniqueBeneficiaries":5364},{"code":"87801","totalPaid":94785.67,"totalClaims":1489,"uniqueBeneficiaries":1414},{"code":"87635","totalPaid":91373.61,"totalClaims":2067,"uniqueBeneficiaries":2025},{"code":"87637","totalPaid":77685.81,"totalClaims":581,"uniqueBeneficiaries":573},{"code":"84466","totalPaid":72026.7,"totalClaims":6974,"uniqueBeneficiaries":6858},{"code":"88142","totalPaid":71371.4,"totalClaims":4366,"uniqueBeneficiaries":4289},{"code":"86706","totalPaid":70726.12,"totalClaims":6773,"uniqueBeneficiaries":6640},{"code":"86480","totalPaid":68187.97,"totalClaims":1425,"uniqueBeneficiaries":1391},{"code":"83655","totalPaid":67726.6,"totalClaims":3670,"uniqueBeneficiaries":3650}],"monthlyTrend":[{"month":"2018-01","totalPaid":78350.06,"totalClaims":13831},{"month":"2018-02","totalPaid":54826.79,"totalClaims":11678},{"month":"2018-03","totalPaid":71057.62,"totalClaims":12766},{"month":"2018-04","totalPaid":61319.31,"totalClaims":13291},{"month":"2018-05","totalPaid":55774.38,"totalClaims":12925},{"month":"2018-06","totalPaid":43924.04,"totalClaims":11248},{"month":"2018-07","totalPaid":50189.59,"totalClaims":12264},{"month":"2018-08","totalPaid":52168.2,"totalClaims":12412},{"month":"2018-09","totalPaid":54157.7,"totalClaims":10875},{"month":"2018-10","totalPaid":104076.16,"totalClaims":12720},{"month":"2018-11","totalPaid":152886.13,"totalClaims":11304},{"month":"2018-12","totalPaid":127810.34,"totalClaims":9494},{"month":"2019-01","totalPaid":152915.26,"totalClaims":12463},{"month":"2019-02","totalPaid":130399.51,"totalClaims":10420},{"month":"2019-03","totalPaid":143840.03,"totalClaims":11373},{"month":"2019-04","totalPaid":149589.64,"totalClaims":12327},{"month":"2019-05","totalPaid":149880.56,"totalClaims":12159},{"month":"2019-06","totalPaid":148571.97,"totalClaims":11278},{"month":"2019-07","totalPaid":162668.22,"totalClaims":12170},{"month":"2019-08","totalPaid":162357.11,"totalClaims":12123},{"month":"2019-09","totalPaid":137767.32,"totalClaims":9757},{"month":"2019-10","totalPaid":149673.28,"totalClaims":10970},{"month":"2019-11","totalPaid":113482.81,"totalClaims":8470},{"month":"2019-12","totalPaid":110132.52,"totalClaims":7856},{"month":"2020-01","totalPaid":147118.26,"totalClaims":11263},{"month":"2020-02","totalPaid":115571.28,"totalClaims":9067},{"month":"2020-03","totalPaid":69252.3,"totalClaims":5519},{"month":"2020-04","totalPaid":34006.64,"totalClaims":2451},{"month":"2020-05","totalPaid":98951.23,"totalClaims":4309},{"month":"2020-06","totalPaid":180272.55,"totalClaims":7724},{"month":"2020-07","totalPaid":184755.63,"totalClaims":8140},{"month":"2020-08","totalPaid":124317.25,"totalClaims":7417},{"month":"2020-09","totalPaid":137319.26,"totalClaims":8636},{"month":"2020-10","totalPaid":174214.42,"totalClaims":8736},{"month":"2020-11","totalPaid":196079.83,"totalClaims":8399},{"month":"2020-12","totalPaid":161010.78,"totalClaims":7921},{"month":"2021-01","totalPaid":212383.91,"totalClaims":10689},{"month":"2021-02","totalPaid":196272.29,"totalClaims":10406},{"month":"2021-03","totalPaid":218240.25,"totalClaims":11986},{"month":"2021-04","totalPaid":223478.87,"totalClaims":11231},{"month":"2021-05","totalPaid":199900.56,"totalClaims":10060},{"month":"2021-06","totalPaid":174046.48,"totalClaims":10152},{"month":"2021-07","totalPaid":175767.14,"totalClaims":10032},{"month":"2021-08","totalPaid":195512.33,"totalClaims":10652},{"month":"2021-09","totalPaid":244102.7,"totalClaims":11556},{"month":"2021-10","totalPaid":270162.95,"totalClaims":12038},{"month":"2021-11","totalPaid":289117.08,"totalClaims":12024},{"month":"2021-12","totalPaid":302675.62,"totalClaims":11782},{"month":"2022-01","totalPaid":234670.74,"totalClaims":10088},{"month":"2022-02","totalPaid":118603.06,"totalClaims":7088},{"month":"2022-03","totalPaid":119772.27,"totalClaims":7751},{"month":"2022-04","totalPaid":120289.71,"totalClaims":7843},{"month":"2022-05","totalPaid":113420.61,"totalClaims":7005},{"month":"2022-06","totalPaid":98356.26,"totalClaims":6260},{"month":"2022-07","totalPaid":91054.72,"totalClaims":5844},{"month":"2022-08","totalPaid":117699.26,"totalClaims":8364},{"month":"2022-09","totalPaid":130535.75,"totalClaims":8985},{"month":"2022-10","totalPaid":133738.58,"totalClaims":9191},{"month":"2022-11","totalPaid":126171.7,"totalClaims":8175},{"month":"2022-12","totalPaid":109057.9,"totalClaims":7846},{"month":"2023-01","totalPaid":125875.42,"totalClaims":9905},{"month":"2023-02","totalPaid":109075.89,"totalClaims":8421},{"month":"2023-03","totalPaid":124205.03,"totalClaims":10199},{"month":"2023-04","totalPaid":104021.39,"totalClaims":8434},{"month":"2023-05","totalPaid":121145.95,"totalClaims":9700},{"month":"2023-06","totalPaid":106031.47,"totalClaims":8776},{"month":"2023-07","totalPaid":95023.61,"totalClaims":8155},{"month":"2023-08","totalPaid":130486.38,"totalClaims":10343},{"month":"2023-09","totalPaid":107793.49,"totalClaims":8892},{"month":"2023-10","totalPaid":121997.04,"totalClaims":9595},{"month":"2023-11","totalPaid":125491.32,"totalClaims":9277},{"month":"2023-12","totalPaid":128601.75,"totalClaims":8483},{"month":"2024-01","totalPaid":159799.3,"totalClaims":11411},{"month":"2024-02","totalPaid":164370.41,"totalClaims":10865},{"month":"2024-03","totalPaid":151367.48,"totalClaims":10185},{"month":"2024-04","totalPaid":157090.82,"totalClaims":10486},{"month":"2024-05","totalPaid":149717.06,"totalClaims":9544},{"month":"2024-06","totalPaid":124137.07,"totalClaims":7039},{"month":"2024-07","totalPaid":129363.15,"totalClaims":7564},{"month":"2024-08","totalPaid":120270.98,"totalClaims":7204},{"month":"2024-09","totalPaid":144247.56,"totalClaims":7200},{"month":"2024-10","totalPaid":157558.04,"totalClaims":7658},{"month":"2024-11","totalPaid":121200.06,"totalClaims":6077},{"month":"2024-12","totalPaid":84474.85,"totalClaims":3982}]}