{"npi":"1225476021","totalPaid":8066228.61,"totalClaims":81251,"totalBeneficiaries":16215,"uniqueCodes":3,"activeMonths":70,"procedures":[{"code":"S0215","totalPaid":7444392.29,"totalClaims":37899,"uniqueBeneficiaries":7050},{"code":"A0120","totalPaid":545582.59,"totalClaims":37884,"uniqueBeneficiaries":7050},{"code":"T2007","totalPaid":76253.73,"totalClaims":5468,"uniqueBeneficiaries":2115}],"monthlyTrend":[{"month":"2018-01","totalPaid":83261.76,"totalClaims":1131},{"month":"2018-02","totalPaid":72324.55,"totalClaims":978},{"month":"2018-03","totalPaid":77300.35,"totalClaims":1080},{"month":"2018-04","totalPaid":80961.61,"totalClaims":1158},{"month":"2018-05","totalPaid":67969.3,"totalClaims":955},{"month":"2018-06","totalPaid":73966.29,"totalClaims":1158},{"month":"2018-07","totalPaid":56095.12,"totalClaims":928},{"month":"2018-08","totalPaid":90549.04,"totalClaims":1272},{"month":"2018-09","totalPaid":59229.69,"totalClaims":711},{"month":"2018-10","totalPaid":103414.69,"totalClaims":1365},{"month":"2018-11","totalPaid":104109.17,"totalClaims":1395},{"month":"2018-12","totalPaid":75454.78,"totalClaims":1037},{"month":"2019-01","totalPaid":68728.66,"totalClaims":960},{"month":"2019-02","totalPaid":67452.74,"totalClaims":890},{"month":"2019-03","totalPaid":77095.75,"totalClaims":1102},{"month":"2019-04","totalPaid":74231.3,"totalClaims":1098},{"month":"2019-05","totalPaid":46906.31,"totalClaims":686},{"month":"2019-06","totalPaid":67975.02,"totalClaims":990},{"month":"2019-07","totalPaid":85645.01,"totalClaims":1182},{"month":"2019-08","totalPaid":80663.32,"totalClaims":1129},{"month":"2019-09","totalPaid":55196.42,"totalClaims":827},{"month":"2019-10","totalPaid":59318.83,"totalClaims":851},{"month":"2019-11","totalPaid":49277.12,"totalClaims":695},{"month":"2019-12","totalPaid":66886.7,"totalClaims":953},{"month":"2020-01","totalPaid":81706.73,"totalClaims":1188},{"month":"2020-02","totalPaid":66229.4,"totalClaims":922},{"month":"2020-03","totalPaid":25808.47,"totalClaims":332},{"month":"2020-08","totalPaid":13292.61,"totalClaims":142},{"month":"2020-09","totalPaid":21695.82,"totalClaims":265},{"month":"2020-10","totalPaid":27582.72,"totalClaims":314},{"month":"2020-11","totalPaid":33000.28,"totalClaims":320},{"month":"2020-12","totalPaid":40651.54,"totalClaims":405},{"month":"2021-01","totalPaid":93615.33,"totalClaims":615},{"month":"2021-02","totalPaid":303941.77,"totalClaims":1586},{"month":"2021-03","totalPaid":499172.56,"totalClaims":2328},{"month":"2021-04","totalPaid":504649.76,"totalClaims":2430},{"month":"2021-05","totalPaid":504292.48,"totalClaims":2414},{"month":"2021-06","totalPaid":466080.25,"totalClaims":2204},{"month":"2021-07","totalPaid":364002.13,"totalClaims":1620},{"month":"2021-08","totalPaid":47448.66,"totalClaims":582},{"month":"2021-09","totalPaid":107874.73,"totalClaims":1296},{"month":"2021-10","totalPaid":129821.96,"totalClaims":1505},{"month":"2021-11","totalPaid":170131.49,"totalClaims":2032},{"month":"2021-12","totalPaid":206366.3,"totalClaims":2452},{"month":"2022-01","totalPaid":227713.6,"totalClaims":2724},{"month":"2022-02","totalPaid":238697.32,"totalClaims":2850},{"month":"2022-03","totalPaid":279125.09,"totalClaims":3342},{"month":"2022-04","totalPaid":251359.66,"totalClaims":2972},{"month":"2022-05","totalPaid":279657.54,"totalClaims":3344},{"month":"2022-06","totalPaid":301020.33,"totalClaims":3564},{"month":"2022-07","totalPaid":84328.51,"totalClaims":1009},{"month":"2022-08","totalPaid":114228.49,"totalClaims":1375},{"month":"2022-09","totalPaid":96934.86,"totalClaims":1358},{"month":"2022-10","totalPaid":60022.56,"totalClaims":889},{"month":"2022-11","totalPaid":59409.38,"totalClaims":903},{"month":"2022-12","totalPaid":59801.39,"totalClaims":861},{"month":"2023-01","totalPaid":43434.82,"totalClaims":575},{"month":"2023-02","totalPaid":22804.95,"totalClaims":310},{"month":"2023-03","totalPaid":41834.0,"totalClaims":521},{"month":"2023-04","totalPaid":33366.35,"totalClaims":388},{"month":"2023-05","totalPaid":25985.45,"totalClaims":311},{"month":"2023-06","totalPaid":28451.39,"totalClaims":310},{"month":"2023-07","totalPaid":36364.73,"totalClaims":393},{"month":"2023-08","totalPaid":54699.27,"totalClaims":638},{"month":"2023-09","totalPaid":62206.34,"totalClaims":684},{"month":"2023-10","totalPaid":68451.62,"totalClaims":762},{"month":"2023-11","totalPaid":66127.88,"totalClaims":766},{"month":"2023-12","totalPaid":51004.93,"totalClaims":548},{"month":"2024-01","totalPaid":20682.79,"totalClaims":296},{"month":"2024-02","totalPaid":7136.84,"totalClaims":75}]}