{"npi":"1427441435","totalPaid":10324751.8,"totalClaims":137746,"totalBeneficiaries":50594,"uniqueCodes":11,"activeMonths":84,"procedures":[{"code":"H0020","totalPaid":7364355.02,"totalClaims":98304,"uniqueBeneficiaries":23579},{"code":"H0004","totalPaid":2043215.65,"totalClaims":28367,"uniqueBeneficiaries":18618},{"code":"H0016","totalPaid":214893.29,"totalClaims":897,"uniqueBeneficiaries":868},{"code":"H0001","totalPaid":182373.2,"totalClaims":1096,"uniqueBeneficiaries":1087},{"code":"99212","totalPaid":172323.52,"totalClaims":3774,"uniqueBeneficiaries":2991},{"code":"99213","totalPaid":156619.25,"totalClaims":1899,"uniqueBeneficiaries":1723},{"code":"H0047","totalPaid":95119.49,"totalClaims":1284,"uniqueBeneficiaries":518},{"code":"H0005","totalPaid":62273.26,"totalClaims":1483,"uniqueBeneficiaries":757},{"code":"99214","totalPaid":24081.47,"totalClaims":217,"uniqueBeneficiaries":207},{"code":"99211","totalPaid":5031.54,"totalClaims":225,"uniqueBeneficiaries":193},{"code":"G2067","totalPaid":4466.11,"totalClaims":200,"uniqueBeneficiaries":53}],"monthlyTrend":[{"month":"2018-01","totalPaid":86232.17,"totalClaims":1418},{"month":"2018-02","totalPaid":86695.32,"totalClaims":1403},{"month":"2018-03","totalPaid":98420.97,"totalClaims":1614},{"month":"2018-04","totalPaid":85069.61,"totalClaims":1356},{"month":"2018-05","totalPaid":107499.84,"totalClaims":1601},{"month":"2018-06","totalPaid":121811.32,"totalClaims":1642},{"month":"2018-07","totalPaid":129884.18,"totalClaims":1850},{"month":"2018-08","totalPaid":155615.05,"totalClaims":2344},{"month":"2018-09","totalPaid":125820.72,"totalClaims":1889},{"month":"2018-10","totalPaid":145462.9,"totalClaims":2066},{"month":"2018-11","totalPaid":159474.37,"totalClaims":2439},{"month":"2018-12","totalPaid":133206.43,"totalClaims":2044},{"month":"2019-01","totalPaid":149938.33,"totalClaims":2202},{"month":"2019-02","totalPaid":123796.37,"totalClaims":1817},{"month":"2019-03","totalPaid":131872.88,"totalClaims":1920},{"month":"2019-04","totalPaid":130675.55,"totalClaims":1962},{"month":"2019-05","totalPaid":148307.54,"totalClaims":2197},{"month":"2019-06","totalPaid":124487.76,"totalClaims":1826},{"month":"2019-07","totalPaid":133271.91,"totalClaims":1892},{"month":"2019-08","totalPaid":145613.08,"totalClaims":2146},{"month":"2019-09","totalPaid":118162.98,"totalClaims":1713},{"month":"2019-10","totalPaid":131285.81,"totalClaims":1940},{"month":"2019-11","totalPaid":105098.51,"totalClaims":1579},{"month":"2019-12","totalPaid":102014.78,"totalClaims":1516},{"month":"2020-01","totalPaid":150742.18,"totalClaims":2277},{"month":"2020-02","totalPaid":126920.61,"totalClaims":1833},{"month":"2020-03","totalPaid":129458.9,"totalClaims":1887},{"month":"2020-04","totalPaid":149773.94,"totalClaims":2094},{"month":"2020-05","totalPaid":128500.17,"totalClaims":1823},{"month":"2020-06","totalPaid":140659.4,"totalClaims":1925},{"month":"2020-07","totalPaid":181855.9,"totalClaims":2600},{"month":"2020-08","totalPaid":159225.9,"totalClaims":2155},{"month":"2020-09","totalPaid":129323.78,"totalClaims":1715},{"month":"2020-10","totalPaid":123123.1,"totalClaims":1629},{"month":"2020-11","totalPaid":143949.48,"totalClaims":1922},{"month":"2020-12","totalPaid":127977.65,"totalClaims":1707},{"month":"2021-01","totalPaid":154113.34,"totalClaims":2031},{"month":"2021-02","totalPaid":128164.7,"totalClaims":1676},{"month":"2021-03","totalPaid":142165.85,"totalClaims":1832},{"month":"2021-04","totalPaid":138529.57,"totalClaims":1778},{"month":"2021-05","totalPaid":151168.09,"totalClaims":1946},{"month":"2021-06","totalPaid":124730.98,"totalClaims":1581},{"month":"2021-07","totalPaid":123990.48,"totalClaims":1569},{"month":"2021-08","totalPaid":146023.96,"totalClaims":1944},{"month":"2021-09","totalPaid":124580.01,"totalClaims":1734},{"month":"2021-10","totalPaid":136487.7,"totalClaims":1881},{"month":"2021-11","totalPaid":112864.76,"totalClaims":1596},{"month":"2021-12","totalPaid":114576.36,"totalClaims":1653},{"month":"2022-01","totalPaid":137100.95,"totalClaims":1904},{"month":"2022-02","totalPaid":113449.14,"totalClaims":1525},{"month":"2022-03","totalPaid":119461.07,"totalClaims":1644},{"month":"2022-04","totalPaid":119293.42,"totalClaims":1568},{"month":"2022-05","totalPaid":130217.43,"totalClaims":1697},{"month":"2022-06","totalPaid":109586.38,"totalClaims":1458},{"month":"2022-07","totalPaid":209488.1,"totalClaims":2810},{"month":"2022-08","totalPaid":171052.06,"totalClaims":1755},{"month":"2022-09","totalPaid":120099.19,"totalClaims":1580},{"month":"2022-10","totalPaid":143917.55,"totalClaims":1707},{"month":"2022-11","totalPaid":126333.33,"totalClaims":1501},{"month":"2022-12","totalPaid":114374.4,"totalClaims":1376},{"month":"2023-01","totalPaid":136993.1,"totalClaims":1633},{"month":"2023-02","totalPaid":116346.36,"totalClaims":1359},{"month":"2023-03","totalPaid":118056.27,"totalClaims":1369},{"month":"2023-04","totalPaid":131713.28,"totalClaims":1595},{"month":"2023-05","totalPaid":102586.61,"totalClaims":1275},{"month":"2023-06","totalPaid":103070.85,"totalClaims":1242},{"month":"2023-07","totalPaid":127711.82,"totalClaims":1475},{"month":"2023-08","totalPaid":103160.67,"totalClaims":1206},{"month":"2023-09","totalPaid":107156.53,"totalClaims":1243},{"month":"2023-10","totalPaid":117395.45,"totalClaims":1373},{"month":"2023-11","totalPaid":94816.98,"totalClaims":1100},{"month":"2023-12","totalPaid":101060.11,"totalClaims":1224},{"month":"2024-01","totalPaid":90682.12,"totalClaims":1031},{"month":"2024-02","totalPaid":82292.52,"totalClaims":873},{"month":"2024-03","totalPaid":109696.89,"totalClaims":1177},{"month":"2024-04","totalPaid":89349.94,"totalClaims":951},{"month":"2024-05","totalPaid":90500.54,"totalClaims":941},{"month":"2024-06","totalPaid":107021.55,"totalClaims":1120},{"month":"2024-07","totalPaid":91475.98,"totalClaims":995},{"month":"2024-08","totalPaid":87796.26,"totalClaims":931},{"month":"2024-09","totalPaid":95983.75,"totalClaims":1054},{"month":"2024-10","totalPaid":89426.37,"totalClaims":1028},{"month":"2024-11","totalPaid":93495.71,"totalClaims":1071},{"month":"2024-12","totalPaid":53963.93,"totalClaims":791}]}