{"npi":"1710093372","totalPaid":9320503.49,"totalClaims":13324,"totalBeneficiaries":10758,"uniqueCodes":3,"activeMonths":82,"procedures":[{"code":"A0427","totalPaid":4958638.82,"totalClaims":3608,"uniqueBeneficiaries":3012},{"code":"A0429","totalPaid":4130328.64,"totalClaims":2961,"uniqueBeneficiaries":2420},{"code":"A0425","totalPaid":231536.03,"totalClaims":6755,"uniqueBeneficiaries":5326}],"monthlyTrend":[{"month":"2018-01","totalPaid":11166.57,"totalClaims":138},{"month":"2018-02","totalPaid":8173.54,"totalClaims":131},{"month":"2018-03","totalPaid":8399.4,"totalClaims":121},{"month":"2018-04","totalPaid":6312.34,"totalClaims":100},{"month":"2018-05","totalPaid":10162.51,"totalClaims":154},{"month":"2018-06","totalPaid":5828.72,"totalClaims":86},{"month":"2018-07","totalPaid":11448.95,"totalClaims":133},{"month":"2018-08","totalPaid":2674.58,"totalClaims":44},{"month":"2018-09","totalPaid":5865.95,"totalClaims":125},{"month":"2018-10","totalPaid":5060.77,"totalClaims":93},{"month":"2018-11","totalPaid":10695.85,"totalClaims":146},{"month":"2018-12","totalPaid":9553.69,"totalClaims":145},{"month":"2019-01","totalPaid":11519.68,"totalClaims":158},{"month":"2019-02","totalPaid":9266.59,"totalClaims":145},{"month":"2019-03","totalPaid":11899.96,"totalClaims":136},{"month":"2019-04","totalPaid":8640.37,"totalClaims":135},{"month":"2019-05","totalPaid":13779.54,"totalClaims":174},{"month":"2019-06","totalPaid":20267.85,"totalClaims":199},{"month":"2019-07","totalPaid":10676.65,"totalClaims":134},{"month":"2019-08","totalPaid":13240.26,"totalClaims":162},{"month":"2019-09","totalPaid":16486.98,"totalClaims":199},{"month":"2019-10","totalPaid":36576.81,"totalClaims":286},{"month":"2019-11","totalPaid":30918.6,"totalClaims":219},{"month":"2019-12","totalPaid":29587.48,"totalClaims":220},{"month":"2020-01","totalPaid":86320.66,"totalClaims":265},{"month":"2020-02","totalPaid":86859.92,"totalClaims":282},{"month":"2020-03","totalPaid":63183.93,"totalClaims":183},{"month":"2020-04","totalPaid":75280.23,"totalClaims":195},{"month":"2020-05","totalPaid":94547.65,"totalClaims":247},{"month":"2020-06","totalPaid":96555.99,"totalClaims":203},{"month":"2020-07","totalPaid":75215.23,"totalClaims":178},{"month":"2020-08","totalPaid":72570.54,"totalClaims":191},{"month":"2020-09","totalPaid":84270.45,"totalClaims":172},{"month":"2020-10","totalPaid":89274.57,"totalClaims":166},{"month":"2020-11","totalPaid":114558.83,"totalClaims":180},{"month":"2020-12","totalPaid":95446.2,"totalClaims":169},{"month":"2021-01","totalPaid":121553.36,"totalClaims":172},{"month":"2021-02","totalPaid":113641.52,"totalClaims":146},{"month":"2021-03","totalPaid":114648.14,"totalClaims":160},{"month":"2021-05","totalPaid":169.72,"totalClaims":18},{"month":"2021-06","totalPaid":137.72,"totalClaims":18},{"month":"2021-07","totalPaid":18711.27,"totalClaims":55},{"month":"2021-08","totalPaid":97392.01,"totalClaims":108},{"month":"2021-09","totalPaid":213169.76,"totalClaims":171},{"month":"2021-10","totalPaid":217714.81,"totalClaims":176},{"month":"2021-11","totalPaid":195676.12,"totalClaims":179},{"month":"2021-12","totalPaid":203657.78,"totalClaims":202},{"month":"2022-01","totalPaid":68180.26,"totalClaims":98},{"month":"2022-02","totalPaid":76909.72,"totalClaims":94},{"month":"2022-03","totalPaid":193730.93,"totalClaims":165},{"month":"2022-04","totalPaid":212820.09,"totalClaims":205},{"month":"2022-05","totalPaid":176374.9,"totalClaims":174},{"month":"2022-06","totalPaid":231165.65,"totalClaims":222},{"month":"2022-07","totalPaid":279091.66,"totalClaims":225},{"month":"2022-08","totalPaid":202859.43,"totalClaims":177},{"month":"2022-09","totalPaid":212035.55,"totalClaims":179},{"month":"2022-10","totalPaid":233987.5,"totalClaims":189},{"month":"2022-11","totalPaid":192170.59,"totalClaims":158},{"month":"2022-12","totalPaid":254350.24,"totalClaims":215},{"month":"2023-01","totalPaid":189226.62,"totalClaims":170},{"month":"2023-02","totalPaid":202445.39,"totalClaims":171},{"month":"2023-03","totalPaid":231167.6,"totalClaims":196},{"month":"2023-04","totalPaid":165319.13,"totalClaims":145},{"month":"2023-05","totalPaid":239837.83,"totalClaims":201},{"month":"2023-06","totalPaid":239017.91,"totalClaims":212},{"month":"2023-07","totalPaid":259985.54,"totalClaims":208},{"month":"2023-08","totalPaid":219877.15,"totalClaims":186},{"month":"2023-09","totalPaid":257044.71,"totalClaims":226},{"month":"2023-10","totalPaid":214823.75,"totalClaims":180},{"month":"2023-11","totalPaid":171398.9,"totalClaims":147},{"month":"2023-12","totalPaid":243495.74,"totalClaims":210},{"month":"2024-01","totalPaid":131673.05,"totalClaims":126},{"month":"2024-02","totalPaid":165103.28,"totalClaims":150},{"month":"2024-03","totalPaid":199672.0,"totalClaims":169},{"month":"2024-04","totalPaid":201465.0,"totalClaims":179},{"month":"2024-05","totalPaid":164227.89,"totalClaims":145},{"month":"2024-06","totalPaid":232007.04,"totalClaims":206},{"month":"2024-07","totalPaid":183578.56,"totalClaims":156},{"month":"2024-08","totalPaid":136363.25,"totalClaims":125},{"month":"2024-09","totalPaid":137547.54,"totalClaims":129},{"month":"2024-10","totalPaid":134391.75,"totalClaims":124},{"month":"2024-11","totalPaid":28397.29,"totalClaims":43}]}