{"code": "G1011", "providerCount": 17, "topProviders": [{"npi": "1588659528", "name": "RHODE ISLAND HOSPITAL", "city": "PROVIDENCE", "state": "RI", "specialty": "General Acute Care Hospital", "totalPaid": 14769.36, "claims": 215, "beneficiaries": 178, "costPerClaim": 68.69, "tier": "p99", "vsMedian": 245.3}, {"npi": "1487649430", "name": "THE MIRIAM HOSPITAL", "city": "PROVIDENCE", "state": "RI", "specialty": "General Acute Care Hospital", "totalPaid": 950.68, "claims": 21, "beneficiaries": 15, "costPerClaim": 45.27, "tier": "p75", "vsMedian": 161.7}, {"npi": "1689783185", "name": "", "city": "", "state": "", "specialty": "", "totalPaid": 519.05, "claims": 5340, "beneficiaries": 4221, "costPerClaim": 0.1, "tier": "below_median", "vsMedian": 0.3}, {"npi": "1144228446", "name": "", "city": "", "state": "", "specialty": "", "totalPaid": 23.58, "claims": 83, "beneficiaries": 77, "costPerClaim": 0.28, "tier": "above_median", "vsMedian": 1.0}, {"npi": "1295736015", "name": "", "city": "", "state": "", "specialty": "", "totalPaid": 0.01, "claims": 26, "beneficiaries": 17, "costPerClaim": 0.0, "tier": "below_median", "vsMedian": 0.0}, {"npi": "1275979825", "name": "", "city": "", "state": "", "specialty": "", "totalPaid": 0.0, "claims": 12, "beneficiaries": 12, "costPerClaim": 0, "tier": "below_median", "vsMedian": 0.0}, {"npi": "1053345652", "name": "", "city": "", "state": "", "specialty": "", "totalPaid": 0.0, "claims": 55, "beneficiaries": 47, "costPerClaim": 0, "tier": "below_median", "vsMedian": 0.0}, {"npi": "1518913607", "name": "", "city": "", "state": "", "specialty": "", "totalPaid": 0.0, "claims": 48, "beneficiaries": 40, "costPerClaim": 0, "tier": "below_median", "vsMedian": 0.0}, {"npi": "1518952761", "name": "", "city": "", "state": "", "specialty": "", "totalPaid": 0.0, "claims": 15, "beneficiaries": 14, "costPerClaim": 0, "tier": "below_median", "vsMedian": 0.0}, {"npi": "1205882396", "name": "", "city": "", "state": "", "specialty": "", "totalPaid": 0.0, "claims": 12, "beneficiaries": 12, "costPerClaim": 0, "tier": "below_median", "vsMedian": 0.0}, {"npi": "1598708513", "name": "", "city": "", "state": "", "specialty": "", "totalPaid": 0.0, "claims": 14, "beneficiaries": 13, "costPerClaim": 0, "tier": "below_median", "vsMedian": 0.0}, {"npi": "1770693939", "name": "", "city": "", "state": "", "specialty": "", "totalPaid": 0.0, "claims": 78, "beneficiaries": 72, "costPerClaim": 0, "tier": "below_median", "vsMedian": 0.0}, {"npi": "1295728491", "name": "", "city": "", "state": "", "specialty": "", "totalPaid": 0.0, "claims": 46, "beneficiaries": 38, "costPerClaim": 0, "tier": "below_median", "vsMedian": 0.0}, {"npi": "1619914785", "name": "", "city": "", "state": "", "specialty": "", "totalPaid": 0.0, "claims": 18, "beneficiaries": 12, "costPerClaim": 0, "tier": "below_median", "vsMedian": 0.0}, {"npi": "1679677983", "name": "", "city": "", "state": "", "specialty": "", "totalPaid": 0.0, "claims": 15, "beneficiaries": 13, "costPerClaim": 0, "tier": "below_median", "vsMedian": 0.0}, {"npi": "1083697718", "name": "", "city": "", "state": "", "specialty": "", "totalPaid": 0.0, "claims": 47, "beneficiaries": 24, "costPerClaim": 0, "tier": "below_median", "vsMedian": 0.0}, {"npi": "1720017528", "name": "", "city": "", "state": "", "specialty": "", "totalPaid": 0.0, "claims": 120, "beneficiaries": 110, "costPerClaim": 0, "tier": "below_median", "vsMedian": 0.0}]}