{"code": "OP637", "providerCount": 38, "topProviders": [{"npi": "1689744856", "name": "JERSEY CITY MEDICAL CENTER", "city": "JERSEY CITY", "state": "NJ", "specialty": "General Acute Care Hospital", "totalPaid": 35029.740000000005, "claims": 8972, "beneficiaries": 5736, "costPerClaim": 3.9, "tier": "p99", "vsMedian": 7.8}, {"npi": "1255419651", "name": "", "city": "", "state": "", "specialty": "", "totalPaid": 16485.100000000002, "claims": 19851, "beneficiaries": 6115, "costPerClaim": 0.83, "tier": "above_median", "vsMedian": 1.7}, {"npi": "1386746592", "name": "KENNEDY UNIVERSITY HOSPITAL INC.", "city": "STRATFORD", "state": "NJ", "specialty": "General Acute Care Hospital", "totalPaid": 10051.860000000002, "claims": 2919, "beneficiaries": 1811, "costPerClaim": 3.44, "tier": "p90", "vsMedian": 6.9}, {"npi": "1346243375", "name": "ROBERT WOOD JOHNSON UNIVERSITY HOSPITAL, INC", "city": "NEW BRUNSWICK", "state": "NJ", "specialty": "General Acute Care Hospital", "totalPaid": 7494.9800000000005, "claims": 4866, "beneficiaries": 2095, "costPerClaim": 1.54, "tier": "p90", "vsMedian": 3.1}, {"npi": "1215998323", "name": "UNIVERSITY HOSPITAL", "city": "NEWARK", "state": "NJ", "specialty": "General Acute Care Hospital", "totalPaid": 2586.19, "claims": 3132, "beneficiaries": 2334, "costPerClaim": 0.83, "tier": "above_median", "vsMedian": 1.7}, {"npi": "1215027966", "name": "NEWARK BETH ISRAEL MEDICAL CENTER INC", "city": "NEWARK", "state": "NJ", "specialty": "General Acute Care Hospital", "totalPaid": 2130.2599999999998, "claims": 3687, "beneficiaries": 2119, "costPerClaim": 0.58, "tier": "above_median", "vsMedian": 1.2}, {"npi": "1982720249", "name": "", "city": "", "state": "", "specialty": "", "totalPaid": 1898.1799999999998, "claims": 1296, "beneficiaries": 964, "costPerClaim": 1.46, "tier": "p75", "vsMedian": 2.9}, {"npi": "1013386143", "name": "", "city": "", "state": "", "specialty": "", "totalPaid": 1639.32, "claims": 1858, "beneficiaries": 952, "costPerClaim": 0.88, "tier": "p75", "vsMedian": 1.8}, {"npi": "1902901333", "name": "CLARA MAASS MEDICAL CENTER", "city": "BELLEVILLE", "state": "NJ", "specialty": "General Acute Care Hospital", "totalPaid": 1594.0200000000002, "claims": 2124, "beneficiaries": 1271, "costPerClaim": 0.75, "tier": "above_median", "vsMedian": 1.5}, {"npi": "1457456279", "name": "HMH HOSPITALS CORPORATION", "city": "HACKENSACK", "state": "NJ", "specialty": "Ambulance", "totalPaid": 1508.3600000000001, "claims": 9038, "beneficiaries": 4359, "costPerClaim": 0.17, "tier": "below_median", "vsMedian": 0.3}, {"npi": "1366097032", "name": "", "city": "", "state": "", "specialty": "", "totalPaid": 1422.5500000000002, "claims": 4155, "beneficiaries": 2378, "costPerClaim": 0.34, "tier": "below_median", "vsMedian": 0.7}, {"npi": "1700887411", "name": "MEMORIAL HOSPITAL FOR CANCER AND ALLIED DISEASES", "city": "NEW YORK", "state": "NY", "specialty": "Pharmacy", "totalPaid": 1285.94, "claims": 700, "beneficiaries": 381, "costPerClaim": 1.84, "tier": "p90", "vsMedian": 3.7}, {"npi": "1013010917", "name": "", "city": "", "state": "", "specialty": "", "totalPaid": 1255.97, "claims": 1846, "beneficiaries": 869, "costPerClaim": 0.68, "tier": "above_median", "vsMedian": 1.4}, {"npi": "1396857488", "name": "COOPERMAN BARNABAS MEDICAL CENTER INC", "city": "LIVINGSTON", "state": "NJ", "specialty": "General Acute Care Hospital", "totalPaid": 1228.2, "claims": 1431, "beneficiaries": 974, "costPerClaim": 0.86, "tier": "above_median", "vsMedian": 1.7}, {"npi": "1609983790", "name": "", "city": "", "state": "", "specialty": "", "totalPaid": 1220.0099999999998, "claims": 1175, "beneficiaries": 656, "costPerClaim": 1.04, "tier": "p75", "vsMedian": 2.1}, {"npi": "1164487542", "name": "INSPIRA MEDICAL CENTERS  INC.", "city": "VINELAND", "state": "NJ", "specialty": "General Acute Care Hospital", "totalPaid": 944.48, "claims": 8678, "beneficiaries": 5481, "costPerClaim": 0.11, "tier": "below_median", "vsMedian": 0.2}, {"npi": "1003236878", "name": "", "city": "", "state": "", "specialty": "", "totalPaid": 928.83, "claims": 1628, "beneficiaries": 719, "costPerClaim": 0.57, "tier": "above_median", "vsMedian": 1.1}, {"npi": "1225133473", "name": "", "city": "", "state": "", "specialty": "", "totalPaid": 925.97, "claims": 690, "beneficiaries": 356, "costPerClaim": 1.34, "tier": "p75", "vsMedian": 2.7}, {"npi": "1629069638", "name": "", "city": "", "state": "", "specialty": "", "totalPaid": 734.4, "claims": 747, "beneficiaries": 392, "costPerClaim": 0.98, "tier": "p75", "vsMedian": 2.0}, {"npi": "1730692344", "name": "", "city": "", "state": "", "specialty": "", "totalPaid": 651.27, "claims": 3711, "beneficiaries": 1866, "costPerClaim": 0.18, "tier": "below_median", "vsMedian": 0.4}, {"npi": "1861486870", "name": "", "city": "", "state": "", "specialty": "", "totalPaid": 401.54999999999995, "claims": 803, "beneficiaries": 485, "costPerClaim": 0.5, "tier": "above_median", "vsMedian": 1.0}, {"npi": "1144894577", "name": "HMH HOSPITALS CORPORATION", "city": "EDISON", "state": "NJ", "specialty": "General Acute Care Hospital", "totalPaid": 346.9200000000001, "claims": 2646, "beneficiaries": 1498, "costPerClaim": 0.13, "tier": "below_median", "vsMedian": 0.3}, {"npi": "1184601288", "name": "", "city": "", "state": "", "specialty": "", "totalPaid": 344.44, "claims": 1856, "beneficiaries": 1282, "costPerClaim": 0.19, "tier": "below_median", "vsMedian": 0.4}, {"npi": "1053316844", "name": "", "city": "", "state": "", "specialty": "", "totalPaid": 335.89, "claims": 371, "beneficiaries": 147, "costPerClaim": 0.91, "tier": "p75", "vsMedian": 1.8}, {"npi": "1235134024", "name": "", "city": "", "state": "", "specialty": "", "totalPaid": 281.19, "claims": 347, "beneficiaries": 129, "costPerClaim": 0.81, "tier": "above_median", "vsMedian": 1.6}, {"npi": "1790297547", "name": "HMH HOSPITALS CORPORATION", "city": "NEPTUNE", "state": "NJ", "specialty": "General Acute Care Hospital", "totalPaid": 176.19, "claims": 19885, "beneficiaries": 2730, "costPerClaim": 0.01, "tier": "below_median", "vsMedian": 0.0}, {"npi": "1255396024", "name": "", "city": "", "state": "", "specialty": "", "totalPaid": 134.03, "claims": 1227, "beneficiaries": 827, "costPerClaim": 0.11, "tier": "below_median", "vsMedian": 0.2}, {"npi": "1437832201", "name": "", "city": "", "state": "", "specialty": "", "totalPaid": 117.47, "claims": 698, "beneficiaries": 414, "costPerClaim": 0.17, "tier": "below_median", "vsMedian": 0.3}, {"npi": "1790297455", "name": "", "city": "", "state": "", "specialty": "", "totalPaid": 69.03999999999999, "claims": 3910, "beneficiaries": 946, "costPerClaim": 0.02, "tier": "below_median", "vsMedian": 0.0}, {"npi": "1659387975", "name": "", "city": "", "state": "", "specialty": "", "totalPaid": 55.03, "claims": 1075, "beneficiaries": 635, "costPerClaim": 0.05, "tier": "below_median", "vsMedian": 0.1}, {"npi": "1831601590", "name": "", "city": "", "state": "", "specialty": "", "totalPaid": 44.73, "claims": 8525, "beneficiaries": 1579, "costPerClaim": 0.01, "tier": "below_median", "vsMedian": 0.0}, {"npi": "1972141091", "name": "", "city": "", "state": "", "specialty": "", "totalPaid": 36.59, "claims": 435, "beneficiaries": 314, "costPerClaim": 0.08, "tier": "below_median", "vsMedian": 0.2}, {"npi": "1477065126", "name": "", "city": "", "state": "", "specialty": "", "totalPaid": 28.52, "claims": 16062, "beneficiaries": 2162, "costPerClaim": 0.0, "tier": "below_median", "vsMedian": 0.0}, {"npi": "1770583999", "name": "TRINITAS REGIONAL MEDICAL CENTER", "city": "ELIZABETH", "state": "NJ", "specialty": "General Acute Care Hospital", "totalPaid": 11.81, "claims": 196, "beneficiaries": 112, "costPerClaim": 0.06, "tier": "below_median", "vsMedian": 0.1}, {"npi": "1760994412", "name": "", "city": "", "state": "", "specialty": "", "totalPaid": 8.0, "claims": 8746, "beneficiaries": 1358, "costPerClaim": 0.0, "tier": "below_median", "vsMedian": 0.0}, {"npi": "1356828172", "name": "", "city": "", "state": "", "specialty": "", "totalPaid": 7.08, "claims": 3749, "beneficiaries": 714, "costPerClaim": 0.0, "tier": "below_median", "vsMedian": 0.0}, {"npi": "1710499462", "name": "", "city": "", "state": "", "specialty": "", "totalPaid": 4.21, "claims": 9759, "beneficiaries": 1193, "costPerClaim": 0.0, "tier": "below_median", "vsMedian": 0.0}, {"npi": "1568442309", "name": "THE COOPER HEALTH SYSTEM", "city": "CAMDEN", "state": "NJ", "specialty": "General Acute Care Hospital", "totalPaid": 0.0, "claims": 345, "beneficiaries": 187, "costPerClaim": 0, "tier": "below_median", "vsMedian": 0.0}]}